[
    {
        "word": "",
        "translation": "",
        "example": null,
        "learned": false,
        "learned_at": null,
        "name": "make up for",
        "phonetic": "/make up for/",
        "spoken_phonetic_us": "/make up for/",
        "search_term": "phrasal verb/compensate",
        "is_phrasal_verb": true,
        "force_generation": false,
        "definitions": [
            {
                "meaning": "Compensar",
                "usage_example": "I will work extra hours to make up for the delay.",
                "pronunciation_guide_es": "",
                "alternative_example": "I will compensate for the delay.",
                "usage_example_es": "Trabajaré horas extra para compensar el retraso.",
                "char_count": "one",
                "usage_context_en": "compensation/problem solving",
                "usage_context_es": "compensación/solución"
            }
        ],
        "group_name": "Phrasal Verbs: Make",
        "category": "Advanced"
    }
]
