[
    {
        "word": "",
        "translation": "",
        "example": null,
        "learned": false,
        "learned_at": null,
        "name": "[TRADUCIR AL FR: number]",
        "phonetic": "",
        "spoken_phonetic_us": "",
        "search_term": "noun/count/essentials",
        "is_phrasal_verb": false,
        "force_generation": false,
        "definitions": [
            {
                "meaning": "number",
                "usage_example": "[TRADUCIR AL FR: What is your phone number?]",
                "pronunciation_guide_es": "[PRONUNCIACIÓN EN FR PARA HABLANTES DE EN]",
                "alternative_example": "",
                "usage_example_es": "What is your phone number?",
                "char_count": "two",
                "usage_context_en": "A symbol used to count (1, 2, 3)",
                "usage_context_es": "[TRADUCIR AL FR: A symbol used to count (1, 2, 3)]",
                "imagePath": "/card_images/nouns/1-basic/1-basic_card_18_def0.avif"
            }
        ],
        "group_name": "General Concepts",
        "category": ""
    },
    {
        "word": "",
        "translation": "",
        "example": null,
        "learned": false,
        "learned_at": null,
        "name": "[TRADUCIR AL FR: one]",
        "phonetic": "",
        "spoken_phonetic_us": "",
        "search_term": "noun/number/essentials",
        "is_phrasal_verb": false,
        "force_generation": false,
        "definitions": [
            {
                "meaning": "one",
                "usage_example": "[TRADUCIR AL FR: I have one brother.]",
                "pronunciation_guide_es": "[PRONUNCIACIÓN EN FR PARA HABLANTES DE EN]",
                "alternative_example": "",
                "usage_example_es": "I have one brother.",
                "char_count": "one",
                "usage_context_en": "The number 1",
                "usage_context_es": "[TRADUCIR AL FR: The number 1]",
                "imagePath": "/card_images/nouns/1-basic/1-basic_card_191_def0.avif"
            }
        ],
        "group_name": "Numbers",
        "category": ""
    },
    {
        "word": "",
        "translation": "",
        "example": null,
        "learned": false,
        "learned_at": null,
        "name": "[TRADUCIR AL FR: two]",
        "phonetic": "",
        "spoken_phonetic_us": "",
        "search_term": "noun/number/essentials",
        "is_phrasal_verb": false,
        "force_generation": false,
        "definitions": [
            {
                "meaning": "two",
                "usage_example": "[TRADUCIR AL FR: I want two apples.]",
                "pronunciation_guide_es": "[PRONUNCIACIÓN EN FR PARA HABLANTES DE EN]",
                "alternative_example": "",
                "usage_example_es": "I want two apples.",
                "char_count": "one",
                "usage_context_en": "The number 2",
                "usage_context_es": "[TRADUCIR AL FR: The number 2]",
                "imagePath": "/card_images/nouns/1-basic/1-basic_card_192_def0.avif"
            }
        ],
        "group_name": "Numbers",
        "category": ""
    },
    {
        "word": "",
        "translation": "",
        "example": null,
        "learned": false,
        "learned_at": null,
        "name": "[TRADUCIR AL FR: three]",
        "phonetic": "",
        "spoken_phonetic_us": "",
        "search_term": "noun/number/essentials",
        "is_phrasal_verb": false,
        "force_generation": false,
        "definitions": [
            {
                "meaning": "three",
                "usage_example": "[TRADUCIR AL FR: It costs three dollars.]",
                "pronunciation_guide_es": "[PRONUNCIACIÓN EN FR PARA HABLANTES DE EN]",
                "alternative_example": "",
                "usage_example_es": "It costs three dollars.",
                "char_count": "one",
                "usage_context_en": "The number 3",
                "usage_context_es": "[TRADUCIR AL FR: The number 3]",
                "imagePath": "/card_images/nouns/1-basic/1-basic_card_193_def0.avif"
            }
        ],
        "group_name": "Numbers",
        "category": ""
    },
    {
        "word": "",
        "translation": "",
        "example": null,
        "learned": false,
        "learned_at": null,
        "name": "[TRADUCIR AL FR: four]",
        "phonetic": "",
        "spoken_phonetic_us": "",
        "search_term": "noun/number/essentials",
        "is_phrasal_verb": false,
        "force_generation": false,
        "definitions": [
            {
                "meaning": "four",
                "usage_example": "[TRADUCIR AL FR: There are four chairs.]",
                "pronunciation_guide_es": "[PRONUNCIACIÓN EN FR PARA HABLANTES DE EN]",
                "alternative_example": "",
                "usage_example_es": "There are four chairs.",
                "char_count": "one",
                "usage_context_en": "The number 4",
                "usage_context_es": "[TRADUCIR AL FR: The number 4]",
                "imagePath": "/card_images/nouns/1-basic/1-basic_card_194_def0.avif"
            }
        ],
        "group_name": "Numbers",
        "category": ""
    },
    {
        "word": "",
        "translation": "",
        "example": null,
        "learned": false,
        "learned_at": null,
        "name": "[TRADUCIR AL FR: five]",
        "phonetic": "",
        "spoken_phonetic_us": "",
        "search_term": "noun/number/essentials",
        "is_phrasal_verb": false,
        "force_generation": false,
        "definitions": [
            {
                "meaning": "five",
                "usage_example": "[TRADUCIR AL FR: I have five fingers.]",
                "pronunciation_guide_es": "[PRONUNCIACIÓN EN FR PARA HABLANTES DE EN]",
                "alternative_example": "",
                "usage_example_es": "I have five fingers.",
                "char_count": "one",
                "usage_context_en": "The number 5",
                "usage_context_es": "[TRADUCIR AL FR: The number 5]",
                "imagePath": "/card_images/nouns/1-basic/1-basic_card_195_def0.avif"
            }
        ],
        "group_name": "Numbers",
        "category": ""
    },
    {
        "word": "",
        "translation": "",
        "example": null,
        "learned": false,
        "learned_at": null,
        "name": "[TRADUCIR AL FR: six]",
        "phonetic": "",
        "spoken_phonetic_us": "",
        "search_term": "noun/number/essentials",
        "is_phrasal_verb": false,
        "force_generation": false,
        "definitions": [
            {
                "meaning": "six",
                "usage_example": "[TRADUCIR AL FR: He is six years old.]",
                "pronunciation_guide_es": "[PRONUNCIACIÓN EN FR PARA HABLANTES DE EN]",
                "alternative_example": "",
                "usage_example_es": "He is six years old.",
                "char_count": "one",
                "usage_context_en": "The number 6",
                "usage_context_es": "[TRADUCIR AL FR: The number 6]",
                "imagePath": "/card_images/nouns/1-basic/1-basic_card_196_def0.avif"
            }
        ],
        "group_name": "Numbers",
        "category": ""
    },
    {
        "word": "",
        "translation": "",
        "example": null,
        "learned": false,
        "learned_at": null,
        "name": "[TRADUCIR AL FR: seven]",
        "phonetic": "",
        "spoken_phonetic_us": "",
        "search_term": "noun/number/essentials",
        "is_phrasal_verb": false,
        "force_generation": false,
        "definitions": [
            {
                "meaning": "seven",
                "usage_example": "[TRADUCIR AL FR: There are seven days in a week.]",
                "pronunciation_guide_es": "[PRONUNCIACIÓN EN FR PARA HABLANTES DE EN]",
                "alternative_example": "",
                "usage_example_es": "There are seven days in a week.",
                "char_count": "two",
                "usage_context_en": "The number 7",
                "usage_context_es": "[TRADUCIR AL FR: The number 7]",
                "imagePath": "/card_images/nouns/1-basic/1-basic_card_197_def0.avif"
            }
        ],
        "group_name": "Numbers",
        "category": ""
    },
    {
        "word": "",
        "translation": "",
        "example": null,
        "learned": false,
        "learned_at": null,
        "name": "[TRADUCIR AL FR: eight]",
        "phonetic": "",
        "spoken_phonetic_us": "",
        "search_term": "noun/number/essentials",
        "is_phrasal_verb": false,
        "force_generation": false,
        "definitions": [
            {
                "meaning": "eight",
                "usage_example": "[TRADUCIR AL FR: The meeting is at eight.]",
                "pronunciation_guide_es": "[PRONUNCIACIÓN EN FR PARA HABLANTES DE EN]",
                "alternative_example": "",
                "usage_example_es": "The meeting is at eight.",
                "char_count": "one",
                "usage_context_en": "The number 8",
                "usage_context_es": "[TRADUCIR AL FR: The number 8]",
                "imagePath": "/card_images/nouns/1-basic/1-basic_card_198_def0.avif"
            }
        ],
        "group_name": "Numbers",
        "category": ""
    },
    {
        "word": "",
        "translation": "",
        "example": null,
        "learned": false,
        "learned_at": null,
        "name": "[TRADUCIR AL FR: nine]",
        "phonetic": "",
        "spoken_phonetic_us": "",
        "search_term": "noun/number/essentials",
        "is_phrasal_verb": false,
        "force_generation": false,
        "definitions": [
            {
                "meaning": "nine",
                "usage_example": "[TRADUCIR AL FR: I have nine dollars.]",
                "pronunciation_guide_es": "[PRONUNCIACIÓN EN FR PARA HABLANTES DE EN]",
                "alternative_example": "",
                "usage_example_es": "I have nine dollars.",
                "char_count": "one",
                "usage_context_en": "The number 9",
                "usage_context_es": "[TRADUCIR AL FR: The number 9]",
                "imagePath": "/card_images/nouns/1-basic/1-basic_card_199_def0.avif"
            }
        ],
        "group_name": "Numbers",
        "category": ""
    },
    {
        "word": "",
        "translation": "",
        "example": null,
        "learned": false,
        "learned_at": null,
        "name": "[TRADUCIR AL FR: ten]",
        "phonetic": "",
        "spoken_phonetic_us": "",
        "search_term": "noun/number/essentials",
        "is_phrasal_verb": false,
        "force_generation": false,
        "definitions": [
            {
                "meaning": "ten",
                "usage_example": "[TRADUCIR AL FR: She has ten cats.]",
                "pronunciation_guide_es": "[PRONUNCIACIÓN EN FR PARA HABLANTES DE EN]",
                "alternative_example": "",
                "usage_example_es": "She has ten cats.",
                "char_count": "one",
                "usage_context_en": "The number 10",
                "usage_context_es": "[TRADUCIR AL FR: The number 10]",
                "imagePath": "/card_images/nouns/1-basic/1-basic_card_200_def0.avif"
            }
        ],
        "group_name": "Numbers",
        "category": ""
    },
    {
        "word": "",
        "translation": "",
        "example": null,
        "learned": false,
        "learned_at": null,
        "name": "[TRADUCIR AL FR: eleven]",
        "phonetic": "",
        "spoken_phonetic_us": "",
        "search_term": "noun/number/essentials",
        "is_phrasal_verb": false,
        "force_generation": false,
        "definitions": [
            {
                "meaning": "eleven",
                "usage_example": "[TRADUCIR AL FR: I have eleven coins.]",
                "pronunciation_guide_es": "[PRONUNCIACIÓN EN FR PARA HABLANTES DE EN]",
                "alternative_example": "",
                "usage_example_es": "I have eleven coins.",
                "char_count": "1",
                "usage_context_en": "The number 11",
                "usage_context_es": "[TRADUCIR AL FR: The number 11]",
                "imagePath": "/card_images/nouns/1-basic/1-basic_card_485_def0.avif"
            }
        ],
        "group_name": "Numbers",
        "category": ""
    },
    {
        "word": "",
        "translation": "",
        "example": null,
        "learned": false,
        "learned_at": null,
        "name": "[TRADUCIR AL FR: twelve]",
        "phonetic": "",
        "spoken_phonetic_us": "",
        "search_term": "noun/number/essentials",
        "is_phrasal_verb": false,
        "force_generation": false,
        "definitions": [
            {
                "meaning": "twelve",
                "usage_example": "[TRADUCIR AL FR: There are twelve months in a year.]",
                "pronunciation_guide_es": "[PRONUNCIACIÓN EN FR PARA HABLANTES DE EN]",
                "alternative_example": "",
                "usage_example_es": "There are twelve months in a year.",
                "char_count": "1",
                "usage_context_en": "The number 12",
                "usage_context_es": "[TRADUCIR AL FR: The number 12]",
                "imagePath": "/card_images/nouns/1-basic/1-basic_card_486_def0.avif"
            }
        ],
        "group_name": "Numbers",
        "category": ""
    },
    {
        "word": "",
        "translation": "",
        "example": null,
        "learned": false,
        "learned_at": null,
        "name": "[TRADUCIR AL FR: thirteen]",
        "phonetic": "",
        "spoken_phonetic_us": "",
        "search_term": "noun/number/essentials",
        "is_phrasal_verb": false,
        "force_generation": false,
        "definitions": [
            {
                "meaning": "thirteen",
                "usage_example": "[TRADUCIR AL FR: He is thirteen years old.]",
                "pronunciation_guide_es": "[PRONUNCIACIÓN EN FR PARA HABLANTES DE EN]",
                "alternative_example": "",
                "usage_example_es": "He is thirteen years old.",
                "char_count": "1",
                "usage_context_en": "The number 13",
                "usage_context_es": "[TRADUCIR AL FR: The number 13]",
                "imagePath": "/card_images/nouns/1-basic/1-basic_card_487_def0.avif"
            }
        ],
        "group_name": "Numbers",
        "category": ""
    },
    {
        "word": "",
        "translation": "",
        "example": null,
        "learned": false,
        "learned_at": null,
        "name": "[TRADUCIR AL FR: fourteen]",
        "phonetic": "",
        "spoken_phonetic_us": "",
        "search_term": "noun/number/essentials",
        "is_phrasal_verb": false,
        "force_generation": false,
        "definitions": [
            {
                "meaning": "fourteen",
                "usage_example": "[TRADUCIR AL FR: We need fourteen chairs.]",
                "pronunciation_guide_es": "[PRONUNCIACIÓN EN FR PARA HABLANTES DE EN]",
                "alternative_example": "",
                "usage_example_es": "We need fourteen chairs.",
                "char_count": "1",
                "usage_context_en": "The number 14",
                "usage_context_es": "[TRADUCIR AL FR: The number 14]",
                "imagePath": "/card_images/nouns/1-basic/1-basic_card_488_def0.avif"
            }
        ],
        "group_name": "Numbers",
        "category": ""
    },
    {
        "word": "",
        "translation": "",
        "example": null,
        "learned": false,
        "learned_at": null,
        "name": "[TRADUCIR AL FR: fifteen]",
        "phonetic": "",
        "spoken_phonetic_us": "",
        "search_term": "noun/number/essentials",
        "is_phrasal_verb": false,
        "force_generation": false,
        "definitions": [
            {
                "meaning": "fifteen",
                "usage_example": "[TRADUCIR AL FR: It's fifteen minutes late.]",
                "pronunciation_guide_es": "[PRONUNCIACIÓN EN FR PARA HABLANTES DE EN]",
                "alternative_example": "",
                "usage_example_es": "It's fifteen minutes late.",
                "char_count": "1",
                "usage_context_en": "The number 15",
                "usage_context_es": "[TRADUCIR AL FR: The number 15]",
                "imagePath": "/card_images/nouns/1-basic/1-basic_card_489_def0.avif"
            }
        ],
        "group_name": "Numbers",
        "category": ""
    },
    {
        "word": "",
        "translation": "",
        "example": null,
        "learned": false,
        "learned_at": null,
        "name": "[TRADUCIR AL FR: sixteen]",
        "phonetic": "",
        "spoken_phonetic_us": "",
        "search_term": "noun/number/essentials",
        "is_phrasal_verb": false,
        "force_generation": false,
        "definitions": [
            {
                "meaning": "sixteen",
                "usage_example": "[TRADUCIR AL FR: She turns sixteen today.]",
                "pronunciation_guide_es": "[PRONUNCIACIÓN EN FR PARA HABLANTES DE EN]",
                "alternative_example": "",
                "usage_example_es": "She turns sixteen today.",
                "char_count": "1",
                "usage_context_en": "The number 16",
                "usage_context_es": "[TRADUCIR AL FR: The number 16]",
                "imagePath": "/card_images/nouns/1-basic/1-basic_card_490_def0.avif"
            }
        ],
        "group_name": "Numbers",
        "category": ""
    },
    {
        "word": "",
        "translation": "",
        "example": null,
        "learned": false,
        "learned_at": null,
        "name": "[TRADUCIR AL FR: seventeen]",
        "phonetic": "",
        "spoken_phonetic_us": "",
        "search_term": "noun/number/essentials",
        "is_phrasal_verb": false,
        "force_generation": false,
        "definitions": [
            {
                "meaning": "seventeen",
                "usage_example": "[TRADUCIR AL FR: There are seventeen students.]",
                "pronunciation_guide_es": "[PRONUNCIACIÓN EN FR PARA HABLANTES DE EN]",
                "alternative_example": "",
                "usage_example_es": "There are seventeen students.",
                "char_count": "1",
                "usage_context_en": "The number 17",
                "usage_context_es": "[TRADUCIR AL FR: The number 17]",
                "imagePath": "/card_images/nouns/1-basic/1-basic_card_491_def0.avif"
            }
        ],
        "group_name": "Numbers",
        "category": ""
    },
    {
        "word": "",
        "translation": "",
        "example": null,
        "learned": false,
        "learned_at": null,
        "name": "[TRADUCIR AL FR: eighteen]",
        "phonetic": "",
        "spoken_phonetic_us": "",
        "search_term": "noun/number/essentials",
        "is_phrasal_verb": false,
        "force_generation": false,
        "definitions": [
            {
                "meaning": "eighteen",
                "usage_example": "[TRADUCIR AL FR: You must be eighteen.]",
                "pronunciation_guide_es": "[PRONUNCIACIÓN EN FR PARA HABLANTES DE EN]",
                "alternative_example": "",
                "usage_example_es": "You must be eighteen.",
                "char_count": "1",
                "usage_context_en": "The number 18",
                "usage_context_es": "[TRADUCIR AL FR: The number 18]",
                "imagePath": "/card_images/nouns/1-basic/1-basic_card_492_def0.avif"
            }
        ],
        "group_name": "Numbers",
        "category": ""
    },
    {
        "word": "",
        "translation": "",
        "example": null,
        "learned": false,
        "learned_at": null,
        "name": "[TRADUCIR AL FR: nineteen]",
        "phonetic": "",
        "spoken_phonetic_us": "",
        "search_term": "noun/number/essentials",
        "is_phrasal_verb": false,
        "force_generation": false,
        "definitions": [
            {
                "meaning": "nineteen",
                "usage_example": "[TRADUCIR AL FR: The book costs nineteen dollars.]",
                "pronunciation_guide_es": "[PRONUNCIACIÓN EN FR PARA HABLANTES DE EN]",
                "alternative_example": "",
                "usage_example_es": "The book costs nineteen dollars.",
                "char_count": "1",
                "usage_context_en": "The number 19",
                "usage_context_es": "[TRADUCIR AL FR: The number 19]",
                "imagePath": "/card_images/nouns/1-basic/1-basic_card_493_def0.avif"
            }
        ],
        "group_name": "Numbers",
        "category": ""
    },
    {
        "word": "",
        "translation": "",
        "example": null,
        "learned": false,
        "learned_at": null,
        "name": "[TRADUCIR AL FR: twenty]",
        "phonetic": "",
        "spoken_phonetic_us": "",
        "search_term": "noun/number/essentials",
        "is_phrasal_verb": false,
        "force_generation": false,
        "definitions": [
            {
                "meaning": "twenty",
                "usage_example": "[TRADUCIR AL FR: I need twenty copies.]",
                "pronunciation_guide_es": "[PRONUNCIACIÓN EN FR PARA HABLANTES DE EN]",
                "alternative_example": "",
                "usage_example_es": "I need twenty copies.",
                "char_count": "1",
                "usage_context_en": "The number 20",
                "usage_context_es": "[TRADUCIR AL FR: The number 20]",
                "imagePath": "/card_images/nouns/1-basic/1-basic_card_494_def0.avif"
            }
        ],
        "group_name": "Numbers",
        "category": ""
    },
    {
        "word": "",
        "translation": "",
        "example": null,
        "learned": false,
        "learned_at": null,
        "name": "[TRADUCIR AL FR: zero]",
        "phonetic": "",
        "spoken_phonetic_us": "",
        "search_term": "noun/numbers/seed",
        "is_phrasal_verb": false,
        "force_generation": false,
        "definitions": [
            {
                "meaning": "zero",
                "usage_example": "[TRADUCIR AL FR: The answer is zero.]",
                "pronunciation_guide_es": "[PRONUNCIACIÓN EN FR PARA HABLANTES DE EN]",
                "alternative_example": "",
                "usage_example_es": "The answer is zero.",
                "char_count": "4",
                "usage_context_en": "The number 0.",
                "usage_context_es": "[TRADUCIR AL FR: The number 0.]",
                "imagePath": "/card_images/nouns/1-basic/seed_zero.avif"
            }
        ],
        "group_name": "Numbers",
        "category": ""
    },
    {
        "word": "",
        "translation": "",
        "example": null,
        "learned": false,
        "learned_at": null,
        "name": "[TRADUCIR AL FR: hundred]",
        "phonetic": "",
        "spoken_phonetic_us": "",
        "search_term": "noun/numbers/seed",
        "is_phrasal_verb": false,
        "force_generation": false,
        "definitions": [
            {
                "meaning": "hundred",
                "usage_example": "[TRADUCIR AL FR: There are one hundred pages.]",
                "pronunciation_guide_es": "[PRONUNCIACIÓN EN FR PARA HABLANTES DE EN]",
                "alternative_example": "",
                "usage_example_es": "There are one hundred pages.",
                "char_count": "7",
                "usage_context_en": "The number 100.",
                "usage_context_es": "[TRADUCIR AL FR: The number 100.]",
                "imagePath": "/card_images/nouns/1-basic/seed_hundred.avif"
            }
        ],
        "group_name": "Numbers",
        "category": ""
    }
]