[
    {
        "word": "",
        "translation": "",
        "example": null,
        "learned": false,
        "learned_at": null,
        "name": "Sorprendentemente",
        "phonetic": "",
        "spoken_phonetic_us": "",
        "search_term": "adverb/sentence",
        "is_phrasal_verb": false,
        "force_generation": false,
        "definitions": [
            {
                "meaning": "[TRADUCIR AL IT: Sorprendentemente]",
                "usage_example": "Sorprendentemente, el examen fue fácil.",
                "pronunciation_guide_es": "[PRONUNCIACIÓN EN ES PARA HABLANTES DE IT]",
                "alternative_example": "",
                "usage_example_es": "[TRADUCIR AL IT: Sorprendentemente, el examen fue fácil.]",
                "char_count": 5,
                "usage_context_en": "[TRADUCIR AL IT: De una manera que causa sorpresa; inesperadamente.]",
                "usage_context_es": "De una manera que causa sorpresa; inesperadamente.",
                "imagePath": ""
            }
        ],
        "group_name": "Adverbs: Sentence",
        "category": ""
    },
    {
        "word": "",
        "translation": "",
        "example": null,
        "learned": false,
        "learned_at": null,
        "name": "Obviamente / Evidentemente",
        "phonetic": "",
        "spoken_phonetic_us": "",
        "search_term": "adverb/sentence/certainty",
        "is_phrasal_verb": false,
        "force_generation": false,
        "definitions": [
            {
                "meaning": "[TRADUCIR AL IT: Obviamente / Evidentemente]",
                "usage_example": "Está cansado. Obviamente, necesita dormir.",
                "pronunciation_guide_es": "[PRONUNCIACIÓN EN ES PARA HABLANTES DE IT]",
                "alternative_example": "",
                "usage_example_es": "[TRADUCIR AL IT: Está cansado. Obviamente, necesita dormir.]",
                "char_count": 6,
                "usage_context_en": "[TRADUCIR AL IT: De una manera que es fácil de ver, entender o estar seguro.]",
                "usage_context_es": "De una manera que es fácil de ver, entender o estar seguro.",
                "imagePath": ""
            }
        ],
        "group_name": "Adverbs: Certainty",
        "category": ""
    },
    {
        "word": "",
        "translation": "",
        "example": null,
        "learned": false,
        "learned_at": null,
        "name": "Aparentemente / Por lo visto",
        "phonetic": "",
        "spoken_phonetic_us": "",
        "search_term": "adverb/sentence/certainty",
        "is_phrasal_verb": false,
        "force_generation": false,
        "definitions": [
            {
                "meaning": "[TRADUCIR AL IT: Aparentemente / Por lo visto]",
                "usage_example": "Aparentemente, la reunión fue cancelada.",
                "pronunciation_guide_es": "[PRONUNCIACIÓN EN ES PARA HABLANTES DE IT]",
                "alternative_example": "",
                "usage_example_es": "[TRADUCIR AL IT: Aparentemente, la reunión fue cancelada.]",
                "char_count": 5,
                "usage_context_en": "[TRADUCIR AL IT: Usado para decir que algo parece verdad basado en lo que oíste o leíste.]",
                "usage_context_es": "Usado para decir que algo parece verdad basado en lo que oíste o leíste.",
                "imagePath": ""
            }
        ],
        "group_name": "Adverbs: Certainty",
        "category": ""
    },
    {
        "word": "",
        "translation": "",
        "example": null,
        "learned": false,
        "learned_at": null,
        "name": "En realidad / De hecho",
        "phonetic": "",
        "spoken_phonetic_us": "",
        "search_term": "adverb/sentence/emphasis",
        "is_phrasal_verb": false,
        "force_generation": false,
        "definitions": [
            {
                "meaning": "[TRADUCIR AL IT: En realidad / De hecho]",
                "usage_example": "Él parece grosero, pero en realidad es muy amable.",
                "pronunciation_guide_es": "[PRONUNCIACIÓN EN ES PARA HABLANTES DE IT]",
                "alternative_example": "",
                "usage_example_es": "[TRADUCIR AL IT: Él parece grosero, pero en realidad es muy amable.]",
                "char_count": "8",
                "usage_context_en": "[TRADUCIR AL IT: Usado para enfatizar que algo es verdad o un hecho.]",
                "usage_context_es": "Usado para enfatizar que algo es verdad o un hecho.",
                "imagePath": ""
            }
        ],
        "group_name": "Adverbs: Sentence",
        "category": ""
    },
    {
        "word": "",
        "translation": "",
        "example": null,
        "learned": false,
        "learned_at": null,
        "name": "Básicamente / En esencia",
        "phonetic": "",
        "spoken_phonetic_us": "",
        "search_term": "adverb/sentence/summary",
        "is_phrasal_verb": false,
        "force_generation": false,
        "definitions": [
            {
                "meaning": "[TRADUCIR AL IT: Básicamente / En esencia]",
                "usage_example": "Básicamente, necesitamos más tiempo.",
                "pronunciation_guide_es": "[PRONUNCIACIÓN EN ES PARA HABLANTES DE IT]",
                "alternative_example": "",
                "usage_example_es": "[TRADUCIR AL IT: Básicamente, necesitamos más tiempo.]",
                "char_count": "5",
                "usage_context_en": "[TRADUCIR AL IT: Usado para introducir el punto más importante o fundamental.]",
                "usage_context_es": "Usado para introducir el punto más importante o fundamental.",
                "imagePath": ""
            }
        ],
        "group_name": "Adverbs: Sentence",
        "category": ""
    }
]