[
  {
    "word": "",
    "translation": "",
    "example": null,
    "learned": false,
    "learned_at": null,
    "definitions": [
      {
        "char_count": "one",
        "meaning": "Empleo / Puesto",
        "pronunciation_guide_es": "/ai_am_LUKing_for_a_NIU_YOB/",
        "usage_context_en": "A paid position of regular employment",
        "usage_context_es": "Un puesto pagado de empleo regular",
        "usage_example": "I am looking for a new job.",
        "usage_example_es": "Estoy buscando un nuevo empleo."
      }
    ],
    "force_generation": false,
    "group_name": "School & Work",
    "is_verb": false,
    "name": "job",
    "phonetic": "/ §…íb/",
    "search_term": "noun/profession/essentials",
    "spoken_phonetic_us": "/ §…Ďňźb/"
  },
  {
    "word": "",
    "translation": "",
    "example": null,
    "learned": false,
    "learned_at": null,
    "definitions": [
      {
        "char_count": "two",
        "meaning": "Doctor / M√©dico",
        "pronunciation_guide_es": "/ai_NID_tu_SI_a_DOKtor/",
        "usage_context_en": "A person who treats sick people",
        "usage_context_es": "Una persona que trata a gente enferma",
        "usage_example": "I need to see a doctor.",
        "usage_example_es": "Necesito ver a un m√©dico."
      }
    ],
    "force_generation": false,
    "group_name": "School & Work",
    "is_verb": false,
    "name": "doctor",
    "phonetic": "/ňąd…íkt…ôr/",
    "search_term": "noun/person/job/essentials",
    "spoken_phonetic_us": "/ňąd…Ďňźkt…ôr/"
  },
  {
    "word": "",
    "translation": "",
    "example": null,
    "learned": false,
    "learned_at": null,
    "definitions": [
      {
        "char_count": "two",
        "meaning": "Polic√≠a",
        "pronunciation_guide_es": "/KOL_de_poLIS/",
        "usage_context_en": "People who enforce laws and stop crime",
        "usage_context_es": "Gente que hace cumplir las leyes y detiene el crimen",
        "usage_example": "Call the police!",
        "usage_example_es": "¬°Llama a la polic√≠a!"
      }
    ],
    "force_generation": false,
    "group_name": "School & Work",
    "is_verb": false,
    "name": "police",
    "phonetic": "/p…ôňąliňźs/",
    "search_term": "noun/job/essentials",
    "spoken_phonetic_us": "/p…ôňąliňźs/"
  },
  {
    "word": "",
    "translation": "",
    "example": null,
    "learned": false,
    "learned_at": null,
    "definitions": [
      {
        "char_count": "three",
        "meaning": "Bombero",
        "pronunciation_guide_es": "/de_FAIRfaiter_is_BREIV/",
        "usage_context_en": "A person who stops fires",
        "usage_context_es": "Una persona que apaga incendios",
        "usage_example": "The firefighter is brave.",
        "usage_example_es": "El bombero es valiente."
      }
    ],
    "force_generation": false,
    "group_name": "School & Work",
    "is_verb": false,
    "name": "firefighter",
    "phonetic": "/ňąfa…™…ôrfa…™t…ôr/",
    "search_term": "noun/job/essentials",
    "spoken_phonetic_us": "/ňąfa…™…ôrfa…™t…ôr/"
  },
  {
    "word": "",
    "translation": "",
    "example": null,
    "learned": false,
    "learned_at": null,
    "definitions": [
      {
        "char_count": "three",
        "meaning": "Gerente / Director",
        "pronunciation_guide_es": "/ai_NID_tu_SPIK_tu_de_MANiyer/",
        "usage_context_en": "A person who controls a business or team",
        "usage_context_es": "Una persona que controla un negocio o equipo",
        "usage_example": "I need to speak to the manager.",
        "usage_example_es": "Necesito hablar con el gerente."
      }
    ],
    "force_generation": false,
    "group_name": "School & Work",
    "is_verb": false,
    "name": "manager",
    "phonetic": "/ňąm√¶n…™ §…ôr/",
    "search_term": "noun/job/work/essentials",
    "spoken_phonetic_us": "/ňąm√¶n…™ §…ôr/"
  },
  {
    "word": "",
    "translation": "",
    "example": null,
    "learned": false,
    "learned_at": null,
    "definitions": [
      {
        "char_count": "three",
        "meaning": "Empleado",
        "pronunciation_guide_es": "/ji_is_a_NIU_emPLOYI/",
        "usage_context_en": "A person who works for money",
        "usage_context_es": "Una persona que trabaja por dinero",
        "usage_example": "He is a new employee.",
        "usage_example_es": "√Čl es un nuevo empleado."
      }
    ],
    "force_generation": false,
    "group_name": "School & Work",
    "is_verb": false,
    "name": "employee",
    "phonetic": "/…õmňąpl…Ē…™iňź/",
    "search_term": "noun/job/work/essentials",
    "spoken_phonetic_us": "/…õmňąpl…Ē…™iňź/"
  },
  {
    "word": "",
    "translation": "",
    "example": null,
    "learned": false,
    "learned_at": null,
    "definitions": [
      {
        "char_count": "three",
        "meaning": "Ingeniero",
        "pronunciation_guide_es": "/shi_is_an_enyinIR/",
        "usage_context_en": "A person who designs buildings or machines",
        "usage_context_es": "Una persona que dise√Īa edificios o m√°quinas",
        "usage_example": "She is an engineer.",
        "usage_example_es": "Ella es ingeniera."
      }
    ],
    "force_generation": false,
    "group_name": "School & Work",
    "is_verb": false,
    "name": "engineer",
    "phonetic": "/ňĆ…õn §…™ňąn…™…ôr/",
    "search_term": "noun/job/work/essentials",
    "spoken_phonetic_us": "/ňĆ…õn §…™ňąn…™r/"
  },
  {
    "word": "",
    "translation": "",
    "example": null,
    "learned": false,
    "learned_at": null,
    "definitions": [
      {
        "char_count": "two",
        "meaning": "Abogado",
        "pronunciation_guide_es": "/ai_NID_tu_KOL_mai_LOIer/",
        "usage_context_en": "A person who helps people with the law",
        "usage_context_es": "Una persona que ayuda a la gente con la ley",
        "usage_example": "I need to call my lawyer.",
        "usage_example_es": "Necesito llamar a mi abogado."
      }
    ],
    "force_generation": false,
    "group_name": "School & Work",
    "is_verb": false,
    "name": "lawyer",
    "phonetic": "/ňąl…Ē…™…ôr/",
    "search_term": "noun/job/work/essentials",
    "spoken_phonetic_us": "/ňąl…Ē…™…ôr/"
  },
  {
    "word": "",
    "translation": "",
    "example": null,
    "learned": false,
    "learned_at": null,
    "definitions": [
      {
        "char_count": "one",
        "meaning": "Enfermero / Enfermera",
        "pronunciation_guide_es": "/de_NORS_JELPT_de_DOKtor/",
        "usage_context_en": "A person who takes care of sick people",
        "usage_context_es": "Una persona que cuida a gente enferma",
        "usage_example": "The nurse helped the doctor.",
        "usage_example_es": "La enfermera ayud√≥ al doctor."
      }
    ],
    "force_generation": false,
    "group_name": "School & Work",
    "is_verb": false,
    "name": "nurse",
    "phonetic": "/n…úňźrs/",
    "search_term": "noun/job/health/essentials",
    "spoken_phonetic_us": "/n…úňźrs/"
  },
  {
    "word": "",
    "translation": "",
    "example": null,
    "learned": false,
    "learned_at": null,
    "definitions": [
      {
        "char_count": "two",
        "meaning": "Artista",
        "pronunciation_guide_es": "/ji_is_a_FEImos_ARtist/",
        "usage_context_en": "A person who creates art (painting, music, etc.)",
        "usage_context_es": "Una persona que crea arte (pintura, m√ļsica, etc.)",
        "usage_example": "He is a famous artist.",
        "usage_example_es": "√Čl es un artista famoso."
      }
    ],
    "force_generation": false,
    "group_name": "School & Work",
    "is_verb": false,
    "name": "artist",
    "phonetic": "/ňą…Ďňźrt…™st/",
    "search_term": "noun/job/art/essentials",
    "spoken_phonetic_us": "/ňą…Ďňźrt…™st/"
  },
  {
    "word": "",
    "translation": "",
    "example": null,
    "learned": false,
    "learned_at": null,
    "definitions": [
      {
        "char_count": "two",
        "meaning": "Escritor",
        "pronunciation_guide_es": "/shi_is_a_FEImos_RAITer/",
        "usage_context_en": "A person who writes books or articles",
        "usage_context_es": "Una persona que escribe libros o art√≠culos",
        "usage_example": "She is a famous writer.",
        "usage_example_es": "Ella es una escritora famosa."
      }
    ],
    "force_generation": false,
    "group_name": "School & Work",
    "is_verb": false,
    "name": "writer",
    "phonetic": "/ňąra…™t…ôr/",
    "search_term": "noun/job/art/essentials",
    "spoken_phonetic_us": "/ňąra…™t…ôr/"
  },
  {
    "word": "",
    "translation": "",
    "example": null,
    "learned": false,
    "learned_at": null,
    "definitions": [
      {
        "char_count": "two",
        "meaning": "Granjero",
        "pronunciation_guide_es": "/de_FARmer_GROUS_KORN/",
        "usage_context_en": "A person who works on a farm",
        "usage_context_es": "Una persona que trabaja en una granja",
        "usage_example": "The farmer grows corn.",
        "usage_example_es": "El granjero cultiva ma√≠z."
      }
    ],
    "force_generation": false,
    "group_name": "School & Work",
    "is_verb": false,
    "name": "farmer",
    "phonetic": "/ňąf…Ďňźrm…ôr/",
    "search_term": "noun/job/nature/essentials",
    "spoken_phonetic_us": "/ňąf…Ďňźrm…ôr/"
  },
  {
    "word": "",
    "translation": "",
    "example": null,
    "learned": false,
    "learned_at": null,
    "definitions": [
      {
        "char_count": "two",
        "meaning": "Conductor / Chofer",
        "pronunciation_guide_es": "/de_BAS_DRAIver/",
        "usage_context_en": "A person who drives a vehicle",
        "usage_context_es": "Una persona que conduce un veh√≠culo",
        "usage_example": "The bus driver.",
        "usage_example_es": "El conductor del autob√ļs."
      }
    ],
    "force_generation": false,
    "group_name": "School & Work",
    "is_verb": false,
    "name": "driver",
    "phonetic": "/ňądra…™v…ôr/",
    "search_term": "noun/job/transport/essentials",
    "spoken_phonetic_us": "/ňądra…™v…ôr/"
  },
  {
    "word": "",
    "translation": "",
    "example": null,
    "learned": false,
    "learned_at": null,
    "definitions": [
      {
        "char_count": "one",
        "usage_example_es": "√Čl es un buen cocinero.",
        "meaning": "Cocinero",
        "pronunciation_guide_es": "/ji_is_a_GUD_KUK/",
        "usage_context_en": "A person who prepares food",
        "usage_context_es": "Una persona que prepara comida",
        "usage_example": "He is a good cook."
      }
    ],
    "force_generation": false,
    "group_name": "School & Work",
    "is_verb": false,
    "name": "cook",
    "phonetic": "/k äk/",
    "search_term": "noun/job/food/essentials",
    "spoken_phonetic_us": "/k äk/"
  },
  {
    "word": "",
    "translation": "",
    "example": null,
    "learned": false,
    "learned_at": null,
    "definitions": [
      {
        "char_count": "one",
        "meaning": "Chef (profesional)",
        "pronunciation_guide_es": "/de_SHEF_at_dis_REStorant_is_FEImos/",
        "usage_context_en": "A professional cook in a restaurant",
        "usage_context_es": "Un cocinero profesional en un restaurante",
        "usage_example": "The chef at this restaurant is famous.",
        "usage_example_es": "El chef de este restaurante es famoso."
      }
    ],
    "force_generation": false,
    "group_name": "School & Work",
    "is_verb": false,
    "name": "chef",
    "phonetic": "/ É…õf/",
    "search_term": "noun/job/food/essentials",
    "spoken_phonetic_us": "/ É…õf/"
  },
  {
    "word": "",
    "translation": "",
    "example": null,
    "learned": false,
    "learned_at": null,
    "definitions": [
      {
        "char_count": "two",
        "meaning": "Mesero / Camarero",
        "pronunciation_guide_es": "/KOL_de_UEIter_PLIS/",
        "usage_context_en": "A man who serves food in a restaurant",
        "usage_context_es": "Un hombre que sirve comida en un restaurante",
        "usage_example": "Call the waiter, please.",
        "usage_example_es": "Llama al mesero, por favor."
      }
    ],
    "force_generation": false,
    "group_name": "School & Work",
    "is_verb": false,
    "name": "waiter",
    "phonetic": "/ňąwe…™t…ôr/",
    "search_term": "noun/job/food/essentials",
    "spoken_phonetic_us": "/ňąwe…™t…ôr/"
  },
  {
    "word": "",
    "translation": "",
    "example": null,
    "learned": false,
    "learned_at": null,
    "definitions": [
      {
        "char_count": "two",
        "usage_example_es": "La mesera es muy amable.",
        "meaning": "Mesera / Camarera",
        "pronunciation_guide_es": "/de_UEItres_is_VERI_NAIS/",
        "usage_context_en": "A woman who serves food in a restaurant",
        "usage_context_es": "Una mujer que sirve comida en un restaurante",
        "usage_example": "The waitress is very nice."
      }
    ],
    "force_generation": false,
    "group_name": "School & Work",
    "is_verb": false,
    "name": "waitress",
    "phonetic": "/ňąwe…™tr…ôs/",
    "search_term": "noun/job/food/essentials",
    "spoken_phonetic_us": "/ňąwe…™tr…ôs/"
  },
  {
    "word": "",
    "translation": "",
    "example": null,
    "learned": false,
    "learned_at": null,
    "definitions": [
      {
        "char_count": "one",
        "meaning": "Jefe",
        "pronunciation_guide_es": "/mai_BOS_is_VERI_diMANding/",
        "usage_context_en": "The person in charge of you at work",
        "usage_context_es": "La persona a cargo de ti en el trabajo",
        "usage_example": "My boss is very demanding.",
        "usage_example_es": "Mi jefe es muy exigente."
      }
    ],
    "force_generation": false,
    "group_name": "School & Work",
    "is_verb": false,
    "name": "boss",
    "phonetic": "/b…ís/",
    "search_term": "noun/job/work/essentials",
    "spoken_phonetic_us": "/b…Ēňźs/"
  },
  {
    "word": "",
    "translation": "",
    "example": null,
    "learned": false,
    "learned_at": null,
    "definitions": [
      {
        "char_count": "two",
        "meaning": "Soldado",
        "pronunciation_guide_es": "/de_SOULyer_JAS_a_IUniform/",
        "usage_context_en": "A person who is in the army",
        "usage_context_es": "Una persona que est√° en el ej√©rcito",
        "usage_example": "The soldier has a uniform.",
        "usage_example_es": "El soldado tiene un uniforme."
      }
    ],
    "force_generation": false,
    "group_name": "School & Work",
    "is_verb": false,
    "name": "soldier",
    "phonetic": "/ňąso äl §…ôr/",
    "search_term": "noun/job/society/essentials",
    "spoken_phonetic_us": "/ňąso äl §…ôr/"
  }
]